flask_beet/__init__.py
flask_beet/forms.py
flask_beet/signals.py
flask_beet/utils.py
flask_beet/views.py
flask_beet/static/img/beet.png
flask_beet/static/js/beet-js.js
flask_beet/templates/_messages.html
flask_beet/templates/layout.html
flask_beet/templates/beet/login-form.html
flask_beet/templates/beet/login.html
Flask_Beet-0.2.0.dist-info/METADATA
Flask_Beet-0.2.0.dist-info/WHEEL
Flask_Beet-0.2.0.dist-info/top_level.txt
Flask_Beet-0.2.0.dist-info/RECORD
