Metadata-Version: 2.1
Name: Flask-Beet
Version: 0.2.0
Summary: A flask extension that allows login via Beet app
Home-page: http://bitshares.eu/
Author: Fabian Schuh
Author-email: fabian@chainsquad.com
License: MIT
Platform: any
Classifier: Environment :: Web Environment
Classifier: Intended Audience :: Developers
Classifier: License :: OSI Approved :: MIT License
Classifier: Operating System :: OS Independent
Classifier: Programming Language :: Python
Classifier: Topic :: Internet :: WWW/HTTP :: Dynamic Content
Classifier: Topic :: Software Development :: Libraries :: Python Modules
Requires-Dist: bitshares
Requires-Dist: Flask
Requires-Dist: Flask-Login
Requires-Dist: Flask-Security
Requires-Dist: Flask-Session
Requires-Dist: SQLAlchemy
Requires-Dist: WTForms
Requires-Dist: Werkzeug
Requires-Dist: blinker
